secure_api/__init__.py
secure_api/src/__init__.py
secure_api/src/secure_api_base.py
secure_api/src/errors/__init__.py
secure_api/src/errors/api_errors.py
secure_api/src/middleware/__init__.py
secure_api/src/middleware/auth_middleware.py
secure_api/src/middleware/cors_middleware.py
secure_api/src/middleware/log_request.py
secure_api/src/middleware/middleware_handler.py
secure_api/src/middleware/rate_limit.py
secure_api/src/modules/__init__.py
secure_api/src/modules/database.py
secure_api/src/modules/enhanced_validator.py
secure_api/src/modules/security.py
secure_api/src/modules/validator.py
secure_api/src/router/__init__.py
secure_api/src/router/router.py
secure_api_py-2.0.1.dist-info/licenses/LICENSE
secure_api_py-2.0.1.dist-info/METADATA
secure_api_py-2.0.1.dist-info/WHEEL
secure_api_py-2.0.1.dist-info/top_level.txt
secure_api_py-2.0.1.dist-info/RECORD
