Metadata-Version: 2.4
Name: secure-api-py
Version: 2.0.1
Summary: A lightweight, modular, and secure framework designed for building RESTful APIs in Appwrite Functions. It provides a streamlined development experience with built-in utilities for request handling, validation, authentication, and database interactions.
Author: MarcusXTechnologies
License: BSD-3-Clause
Project-URL: Homepage, https://github.com/mj-963/secure_api_py
Project-URL: Repository, https://github.com/mj-963/secure_api_py
Project-URL: Issues, https://github.com/mj-963/secure_api_py/issues
Keywords: appwrite,api,rest,framework,functions
Classifier: Development Status :: 4 - Beta
Classifier: Intended Audience :: Developers
Classifier: License :: OSI Approved :: BSD License
Classifier: Programming Language :: Python :: 3
Classifier: Programming Language :: Python :: 3.8
Classifier: Programming Language :: Python :: 3.9
Classifier: Programming Language :: Python :: 3.10
Classifier: Programming Language :: Python :: 3.11
Classifier: Programming Language :: Python :: 3.12
Requires-Python: >=3.8
License-File: LICENSE
Requires-Dist: appwrite>=7.0.0
Dynamic: license-file
